README.md
setup.py
minterbiz/__init__.py
minterbiz/sdk.py
minterbiz/settings.py
minterbiz.egg-info/PKG-INFO
minterbiz.egg-info/SOURCES.txt
minterbiz.egg-info/dependency_links.txt
minterbiz.egg-info/requires.txt
minterbiz.egg-info/top_level.txt