Metadata-Version: 2.1
Name: minterbiz
Version: 1.0.7
Summary: Minter business constructor
Home-page: https://github.com/dinodigital/Open_business
Author: Andrey Gorbunov
Author-email: dinodigital@yandex.ru
License: UNKNOWN
Platform: UNKNOWN
Classifier: Programming Language :: Python :: 3
Classifier: License :: OSI Approved :: MIT License
Classifier: Operating System :: OS Independent
Requires-Python: >=3.6
